{"node":{"d2900379b58859ca3e2c76bdf35af21e9e177b3e":{"workers":{"app/page":9675,"app/details/[id]/page":9675,"app/stream/[id]/page":9675},"layer":{"app/page":"sc_server","app/details/[id]/page":"sc_server","app/stream/[id]/page":"sc_server"}},"632f1550cde791ac75b790c75f59d980bbdbc032":{"workers":{"app/page":9675,"app/details/[id]/page":9675,"app/stream/[id]/page":9675},"layer":{"app/page":"sc_server","app/details/[id]/page":"sc_server","app/stream/[id]/page":"sc_server"}},"5c8afa5ece9f23e816cfa020b8f37ab02d8e8aeb":{"workers":{"app/page":9675,"app/details/[id]/page":9675,"app/stream/[id]/page":9675},"layer":{"app/page":"sc_server","app/details/[id]/page":"sc_server","app/stream/[id]/page":"sc_server"}},"da4b7c383987124e317147d3eae3634a24fab772":{"workers":{"app/page":9675,"app/details/[id]/page":9675,"app/stream/[id]/page":9675},"layer":{"app/page":"sc_server","app/details/[id]/page":"sc_server","app/stream/[id]/page":"sc_server"}}},"edge":{}}